picovoice/LICENSE
picovoice/__init__.py
picovoice/_picovoice.py
picovoice-3.0.4.dist-info/METADATA
picovoice-3.0.4.dist-info/WHEEL
picovoice-3.0.4.dist-info/top_level.txt
picovoice-3.0.4.dist-info/RECORD
